leidenmark/__init__.py
leidenmark/brackets.py
leidenmark/divisions.py
leidenmark/exceptions.py
leidenmark/foreign.py
leidenmark/gaps_spaces.py
leidenmark/glyphs.py
leidenmark/line_nums.py
leidenmark/milestones.py
leidenmark/misc.py
leidenmark/util.py
tests/__init__.py
tests/base_test.py
tests/brackets_test.py
tests/divisions_test.py
tests/glpyhs_test.py
tests/line_nums_test.py
tests/milestones_test.py
tests/misc_test.py
leidenmark-0.2.2.dist-info/LICENSE
leidenmark-0.2.2.dist-info/METADATA
leidenmark-0.2.2.dist-info/WHEEL
leidenmark-0.2.2.dist-info/entry_points.txt
leidenmark-0.2.2.dist-info/top_level.txt
leidenmark-0.2.2.dist-info/RECORD
