Metadata-Version: 2.1
Name: leidenmark
Version: 0.2.2
Summary: A markdown extension for converting Leiden+ epigraphic text to TEI Epidoc XML
Home-page: https://github.com/andredelft/leidenmark
Author: André van Delft
Author-email: andre@delve.nu
License: UNKNOWN
Keywords: Leiden+ Markdown TEI Epidoc XML HTML
Platform: UNKNOWN
Classifier: Development Status :: 4 - Beta
Classifier: Programming Language :: Python :: 3
Requires-Python: >=3.6
Requires-Dist: markdown (<4,>=3.3)
Requires-Dist: lxml (<5,>=4.5)
Requires-Dist: dh-utils (==0.1.23)
Requires-Dist: regex
